{"project":"clb","title":"CLB XML Information Exchange Package Definition","configfile":"clb-cfg.json","reflink":"https://clb.specchain.org/clb-xml/file/refxsd","testlink":"https://clb.specchain.org/clb-xml/file/testdataxml","host":"https://usmtf.specchain.org/clb","port":"8080","dbloc":"tmp/clb-xml/db/clb-xml.db","tempdir":"tmp/","temppath":"tmp/clb-xml/","resources":[{"name":"config","filename":"clb-cfg.json","src":"config/clb-cfg.json","path":"config/clb-cfg.json","description":"CLB XML IEP Configuration Information"},{"name":"refxsd","filename":"usmtf-niem-ref.xsd","src":"xml/xsd/usmtf-niem-ref.xsd","path":"xml/xsd/ext/usmtf-niem-ref.xsd","description":"XML Schema for USMTF-XML Information Exchange Package (IEP) information exchange"},{"name":"iepxsd","filename":"clb-iep.xsd","src":"iepd/clb/xml/xsd/clb-iep.xsd","path":"xml/xsd/clb-iep.xsd","description":"XML Schema for CLB information exchange"},{"name":"xmlschemaxsd","filename":"xml/xsd/ext/w3c/XMLSchema.xsd","src":"xml/xsd/ext/w3c/XMLSchema.xsd","path":"config/clb-cfg.json","description":"W3C XML Schema for XSD validation"},{"name":"xsltxsd","filename":"xslt.xsd","src":"xml/xsd/ext/w3c/xslt.xsd","path":"xml/xsd/ext/w3c/xslt.xsd","description":"W3C XML Schema for XSD validation"},{"name":"iepxsdxsl","filename":"clb-iep.xsl","src":"iepd/clb/xml/xsl/clb-iep.xsl","path":"xml/xsl/clb-iep.xsl","description":"XSLT to generate the CLB Implementation Schema"},{"name":"instancexsl","filename":"clb-instance.xsl","src":"iepd/clb/xml/xsl/clb-instance.xsl","path":"xml/xsl/clb-instance.xsl","description":"XSLT to generate an CLB instance using test values"},{"name":"gogenxsdxsl","filename":"clb-go-gen.xsl","src":"iepd/clb/xml/xsl/clb-go-gen.xsl","path":"xml/xsl/clb-go-gen.xsl","description":"XSLT to generate a GOLANG Struct forCLB information"},{"name":"gotestgenxsl","filename":"clb-go-test-gen.xsl","src":"iepd/clb/xml/xsl/clb-go-test-gen.xsl","path":"xml/xsl/clb-go-test-gen.xsl","description":"XSLT to generate GOLANG Unit Tests for CLB information using test data"},{"name":"xsdjsonxsl","filename":"xsd-json.xsl","src":"xml/xsl/xsd-json.xsl","path":"xml/xsl/common/xsd-json.xsl","description":"Common XSLT utility for generating a JSON representation of an XML Schema"},{"name":"xmljsonxsl","filename":"xml-json.xsl","src":"xml/xsl/xml-json.xsl","path":"xml/xsl/common/xml-json.xsl","description":"Common XSLT utility for generating a JSON representation of an XML Instance"},{"name":"gendocxsl","filename":"docgen.xsl","src":"xml/xsl/docgen.xsl","path":"xml/xsl/common/docgen.xsl","description":"XSLT to generate Documentation from XML Schema"},{"name":"dochtml","filename":"clb-documentation.html","src":"iepd/clb/xml/instance/clb-documentation.html","path":"xml/instance/clb-documentation.html","description":"Autogenerated documentation"},{"name":"zipiepd","filename":"clb-iepd.zip","src":"","path":"clb-iepd.zip","description":"Zipped archive of all Resources"}],"directories":[{"name":"niem","src":"xml/xsd/ext/niem","path":"xml/xsd/ext/niem"},{"name":"ic-xsd","src":"xml/xsd/ext/ic-xsd","path":"xml/xsd/ext/ic-xsd"},{"name":"w3c","src":"xml/xsd/ext/w3c","path":"xml/xsd/ext/w3c"},{"name":"gostruct","src":"src/mtfmsg/clb","path":"src/mtfmsg/clb"},{"name":"gocode","src":"src/xsdprov","path":"src/xsdprov"}]}