{"project":"optaskasw","title":"OPTASKASW XML Information Exchange Package Definition","configfile":"optaskasw-cfg.json","reflink":"https://optaskasw.specchain.org/optaskasw-xml/file/refxsd","testlink":"https://optaskasw.specchain.org/optaskasw-xml/file/testdataxml","host":"https://usmtf.specchain.org/optaskasw","port":"8080","dbloc":"tmp/optaskasw-xml/db/optaskasw-xml.db","tempdir":"tmp/","temppath":"tmp/optaskasw-xml/","resources":[{"name":"config","filename":"optaskasw-cfg.json","src":"config/optaskasw-cfg.json","path":"config/optaskasw-cfg.json","description":"OPTASKASW XML IEP Configuration Information"},{"name":"refxsd","filename":"usmtf-niem-ref.xsd","src":"xml/xsd/usmtf-niem-ref.xsd","path":"xml/xsd/ext/usmtf-niem-ref.xsd","description":"XML Schema for USMTF-XML Information Exchange Package (IEP) information exchange"},{"name":"iepxsd","filename":"optaskasw-iep.xsd","src":"iepd/optaskasw/xml/xsd/optaskasw-iep.xsd","path":"xml/xsd/optaskasw-iep.xsd","description":"XML Schema for OPTASKASW information exchange"},{"name":"xmlschemaxsd","filename":"xml/xsd/ext/w3c/XMLSchema.xsd","src":"xml/xsd/ext/w3c/XMLSchema.xsd","path":"config/optaskasw-cfg.json","description":"W3C XML Schema for XSD validation"},{"name":"xsltxsd","filename":"xslt.xsd","src":"xml/xsd/ext/w3c/xslt.xsd","path":"xml/xsd/ext/w3c/xslt.xsd","description":"W3C XML Schema for XSD validation"},{"name":"iepxsdxsl","filename":"optaskasw-iep.xsl","src":"iepd/optaskasw/xml/xsl/optaskasw-iep.xsl","path":"xml/xsl/optaskasw-iep.xsl","description":"XSLT to generate the OPTASKASW Implementation Schema"},{"name":"instancexsl","filename":"optaskasw-instance.xsl","src":"iepd/optaskasw/xml/xsl/optaskasw-instance.xsl","path":"xml/xsl/optaskasw-instance.xsl","description":"XSLT to generate an OPTASKASW instance using test values"},{"name":"gogenxsdxsl","filename":"optaskasw-go-gen.xsl","src":"iepd/optaskasw/xml/xsl/optaskasw-go-gen.xsl","path":"xml/xsl/optaskasw-go-gen.xsl","description":"XSLT to generate a GOLANG Struct forOPTASKASW information"},{"name":"gotestgenxsl","filename":"optaskasw-go-test-gen.xsl","src":"iepd/optaskasw/xml/xsl/optaskasw-go-test-gen.xsl","path":"xml/xsl/optaskasw-go-test-gen.xsl","description":"XSLT to generate GOLANG Unit Tests for OPTASKASW information using test data"},{"name":"xsdjsonxsl","filename":"xsd-json.xsl","src":"xml/xsl/xsd-json.xsl","path":"xml/xsl/common/xsd-json.xsl","description":"Common XSLT utility for generating a JSON representation of an XML Schema"},{"name":"xmljsonxsl","filename":"xml-json.xsl","src":"xml/xsl/xml-json.xsl","path":"xml/xsl/common/xml-json.xsl","description":"Common XSLT utility for generating a JSON representation of an XML Instance"},{"name":"gendocxsl","filename":"docgen.xsl","src":"xml/xsl/docgen.xsl","path":"xml/xsl/common/docgen.xsl","description":"XSLT to generate Documentation from XML Schema"},{"name":"dochtml","filename":"optaskasw-documentation.html","src":"iepd/optaskasw/xml/instance/optaskasw-documentation.html","path":"xml/instance/optaskasw-documentation.html","description":"Autogenerated documentation"},{"name":"zipiepd","filename":"optaskasw-iepd.zip","src":"","path":"optaskasw-iepd.zip","description":"Zipped archive of all Resources"}],"directories":[{"name":"niem","src":"xml/xsd/ext/niem","path":"xml/xsd/ext/niem"},{"name":"ic-xsd","src":"xml/xsd/ext/ic-xsd","path":"xml/xsd/ext/ic-xsd"},{"name":"w3c","src":"xml/xsd/ext/w3c","path":"xml/xsd/ext/w3c"},{"name":"gostruct","src":"src/mtfmsg/optaskasw","path":"src/mtfmsg/optaskasw"},{"name":"gocode","src":"src/xsdprov","path":"src/xsdprov"}]}