{"project":"USMTF","title":"USMTF-XML Information Exchange Package (IEP)","host":"https://usmtf.specchain.org/","port":"8080","dbloc":"USMTF-XML Information Exchange Package (IEP)","configfile":"config/usmtf-xml-cfg.json","reflink":"https://usmtf.specchain.org/usmtf-xml/file/refxsd","testlink":"https://usmtf.specchain.org/usmtf-xml/file/testdataxml","configurl":"https://usmtf.specchain.org/config","tempdir":"tmp/","temppath":"tmp/usmtf-xml/","resources":[{"name":"refxsd","filename":"usmtf-niem-ref.xsd","src":"xml/xsd/usmtf-niem-ref.xsd","path":"xml/xsd/usmtf-niem-ref.xsd","description":"NIEM Conformant Reference XML Schema for USMTF-XML data"},{"name":"refxsdjson","filename":"usmtf-niem-ref-xsd.json","src":"json/usmtf-niem-ref-xsd.json","path":"json/usmtf-niem-ref-xsd.json","description":"JSON Representation of Reference XML Schema for USMTF-XML data"},{"name":"testdataxml","filename":"usmtf-xml-test-data.xml","src":"xml/instance/usmtf-testdata.xml","path":"xml/instance/usmtf-testdata.xml","description":"Test values for all USMTF-XML data items"},{"name":"dochtml","filename":"usmtf-ref.html","src":"xml/instance/usmtf-ref.html","path":"xml/instance/usmtf-ref.html","description":"Autogenerated documentation"}],"implementations":[{"title":"AKNLDG","name":"aknldg-iep","src":"config/aknldg-cfg.json","srcurl":"https://usmtf.specchain.org/aknldg/file/config","path":"config/aknldg-cfg.json","description":"AKNLDG XML Information Exchange Package"},{"title":"ADMINLOGORD","name":"adminlogord-iep","src":"config/adminlogord-cfg.json","srcurl":"https://usmtf.specchain.org/adminlogord/file/config","path":"config/adminlogord-cfg.json","description":"ADMINLOGORD XML Information Exchange Package"},{"title":"ALLOREQ","name":"alloreq-iep","src":"config/alloreq-cfg.json","srcurl":"https://usmtf.specchain.org/alloreq/file/config","path":"config/alloreq-cfg.json","description":"ALLOREQ XML Information Exchange Package"},{"title":"ABSTAT","name":"abstat-iep","src":"config/abstat-cfg.json","srcurl":"https://usmtf.specchain.org/abstat/file/config","path":"config/abstat-cfg.json","description":"ABSTAT XML Information Exchange Package"},{"title":"AIREVACCONFIRM","name":"airevacconfirm-iep","src":"config/airevacconfirm-cfg.json","srcurl":"https://usmtf.specchain.org/airevacconfirm/file/config","path":"config/airevacconfirm-cfg.json","description":"AIREVACCONFIRM XML Information Exchange Package"},{"title":"AIREVACREQ","name":"airevacreq-iep","src":"config/airevacreq-cfg.json","srcurl":"https://usmtf.specchain.org/airevacreq/file/config","path":"config/airevacreq-cfg.json","description":"AIREVACREQ XML Information Exchange Package"},{"title":"AIREVACRESP","name":"airevacresp-iep","src":"config/airevacresp-cfg.json","srcurl":"https://usmtf.specchain.org/airevacresp/file/config","path":"config/airevacresp-cfg.json","description":"AIREVACRESP XML Information Exchange Package"},{"title":"REQSTATASK","name":"reqstatask-iep","src":"config/reqstatask-cfg.json","srcurl":"https://usmtf.specchain.org/reqstatask/file/config","path":"config/reqstatask-cfg.json","description":"REQSTATASK XML Information Exchange Package"},{"title":"AOD","name":"aod-iep","src":"config/aod-cfg.json","srcurl":"https://usmtf.specchain.org/aod/file/config","path":"config/aod-cfg.json","description":"AOD XML Information Exchange Package"},{"title":"AIRSUPREQ","name":"airsupreq-iep","src":"config/airsupreq-cfg.json","srcurl":"https://usmtf.specchain.org/airsupreq/file/config","path":"config/airsupreq-cfg.json","description":"AIRSUPREQ XML Information Exchange Package"},{"title":"ATO","name":"ato-iep","src":"config/ato-cfg.json","srcurl":"https://usmtf.specchain.org/ato/file/config","path":"config/ato-cfg.json","description":"ATO XML Information Exchange Package"},{"title":"ATONEWS","name":"atonews-iep","src":"config/atonews-cfg.json","srcurl":"https://usmtf.specchain.org/atonews/file/config","path":"config/atonews-cfg.json","description":"ATONEWS XML Information Exchange Package"},{"title":"AFLDREP","name":"afldrep-iep","src":"config/afldrep-cfg.json","srcurl":"https://usmtf.specchain.org/afldrep/file/config","path":"config/afldrep-cfg.json","description":"AFLDREP XML Information Exchange Package"},{"title":"ALMSNSCD","name":"almsnscd-iep","src":"config/almsnscd-cfg.json","srcurl":"https://usmtf.specchain.org/almsnscd/file/config","path":"config/almsnscd-cfg.json","description":"ALMSNSCD XML Information Exchange Package"},{"title":"AIRLIFTREQ","name":"airliftreq-iep","src":"config/airliftreq-cfg.json","srcurl":"https://usmtf.specchain.org/airliftreq/file/config","path":"config/airliftreq-cfg.json","description":"AIRLIFTREQ XML Information Exchange Package"},{"title":"ACO","name":"aco-iep","src":"config/aco-cfg.json","srcurl":"https://usmtf.specchain.org/aco/file/config","path":"config/aco-cfg.json","description":"ACO XML Information Exchange Package"},{"title":"ACMREQ","name":"acmreq-iep","src":"config/acmreq-cfg.json","srcurl":"https://usmtf.specchain.org/acmreq/file/config","path":"config/acmreq-cfg.json","description":"ACMREQ XML Information Exchange Package"},{"title":"ACSAMSTAT","name":"acsamstat-iep","src":"config/acsamstat-cfg.json","srcurl":"https://usmtf.specchain.org/acsamstat/file/config","path":"config/acsamstat-cfg.json","description":"ACSAMSTAT XML Information Exchange Package"},{"title":"ALORD","name":"alord-iep","src":"config/alord-cfg.json","srcurl":"https://usmtf.specchain.org/alord/file/config","path":"config/alord-cfg.json","description":"ALORD XML Information Exchange Package"},{"title":"AFUAMS","name":"afuams-iep","src":"config/afuams-cfg.json","srcurl":"https://usmtf.specchain.org/afuams/file/config","path":"config/afuams-cfg.json","description":"AFUAMS XML Information Exchange Package"},{"title":"AFUASR","name":"afuasr-iep","src":"config/afuasr-cfg.json","srcurl":"https://usmtf.specchain.org/afuasr/file/config","path":"config/afuasr-cfg.json","description":"AFUASR XML Information Exchange Package"},{"title":"AFUDCMD","name":"afudcmd-iep","src":"config/afudcmd-cfg.json","srcurl":"https://usmtf.specchain.org/afudcmd/file/config","path":"config/afudcmd-cfg.json","description":"AFUDCMD XML Information Exchange Package"},{"title":"AFUFUS","name":"afufus-iep","src":"config/afufus-cfg.json","srcurl":"https://usmtf.specchain.org/afufus/file/config","path":"config/afufus-cfg.json","description":"AFUFUS XML Information Exchange Package"},{"title":"AFUFSD","name":"afufsd-iep","src":"config/afufsd-cfg.json","srcurl":"https://usmtf.specchain.org/afufsd/file/config","path":"config/afufsd-cfg.json","description":"AFUFSD XML Information Exchange Package"},{"title":"AFUMFR","name":"afumfr-iep","src":"config/afumfr-cfg.json","srcurl":"https://usmtf.specchain.org/afumfr/file/config","path":"config/afumfr-cfg.json","description":"AFUMFR XML Information Exchange Package"},{"title":"AFUMFN","name":"afumfn-iep","src":"config/afumfn-cfg.json","srcurl":"https://usmtf.specchain.org/afumfn/file/config","path":"config/afumfn-cfg.json","description":"AFUMFN XML Information Exchange Package"},{"title":"AOAFCST","name":"aoafcst-iep","src":"config/aoafcst-cfg.json","srcurl":"https://usmtf.specchain.org/aoafcst/file/config","path":"config/aoafcst-cfg.json","description":"AOAFCST XML Information Exchange Package"},{"title":"ATIATR","name":"atiatr-iep","src":"config/atiatr-cfg.json","srcurl":"https://usmtf.specchain.org/atiatr/file/config","path":"config/atiatr-cfg.json","description":"ATIATR XML Information Exchange Package"},{"title":"ATIIEWTC","name":"atiiewtc-iep","src":"config/atiiewtc-cfg.json","srcurl":"https://usmtf.specchain.org/atiiewtc/file/config","path":"config/atiiewtc-cfg.json","description":"ATIIEWTC XML Information Exchange Package"},{"title":"ATITCRIT","name":"atitcrit-iep","src":"config/atitcrit-cfg.json","srcurl":"https://usmtf.specchain.org/atitcrit/file/config","path":"config/atitcrit-cfg.json","description":"ATITCRIT XML Information Exchange Package"},{"title":"ATITIR","name":"atitir-iep","src":"config/atitir-cfg.json","srcurl":"https://usmtf.specchain.org/atitir/file/config","path":"config/atitir-cfg.json","description":"ATITIR XML Information Exchange Package"},{"title":"ASLTFCST","name":"asltfcst-iep","src":"config/asltfcst-cfg.json","srcurl":"https://usmtf.specchain.org/asltfcst/file/config","path":"config/asltfcst-cfg.json","description":"ASLTFCST XML Information Exchange Package"},{"title":"ASSEMAREA","name":"assemarea-iep","src":"config/assemarea-cfg.json","srcurl":"https://usmtf.specchain.org/assemarea/file/config","path":"config/assemarea-cfg.json","description":"ASSEMAREA XML Information Exchange Package"},{"title":"BDAREPPHASE1","name":"bdarepphase1-iep","src":"config/bdarepphase1-cfg.json","srcurl":"https://usmtf.specchain.org/bdarepphase1/file/config","path":"config/bdarepphase1-cfg.json","description":"BDAREPPHASE1 XML Information Exchange Package"},{"title":"BDAREPPHASE2","name":"bdarepphase2-iep","src":"config/bdarepphase2-cfg.json","srcurl":"https://usmtf.specchain.org/bdarepphase2/file/config","path":"config/bdarepphase2-cfg.json","description":"BDAREPPHASE2 XML Information Exchange Package"},{"title":"BLSNOM","name":"blsnom-iep","src":"config/blsnom-cfg.json","srcurl":"https://usmtf.specchain.org/blsnom/file/config","path":"config/blsnom-cfg.json","description":"BLSNOM XML Information Exchange Package"},{"title":"BLDREP","name":"bldrep-iep","src":"config/bldrep-cfg.json","srcurl":"https://usmtf.specchain.org/bldrep/file/config","path":"config/bldrep-cfg.json","description":"BLDREP XML Information Exchange Package"},{"title":"BLDSHIPREP","name":"bldshiprep-iep","src":"config/bldshiprep-cfg.json","srcurl":"https://usmtf.specchain.org/bldshiprep/file/config","path":"config/bldshiprep-cfg.json","description":"BLDSHIPREP XML Information Exchange Package"},{"title":"BSR","name":"bsr-iep","src":"config/bsr-cfg.json","srcurl":"https://usmtf.specchain.org/bsr/file/config","path":"config/bsr-cfg.json","description":"BSR XML Information Exchange Package"},{"title":"POLALOT","name":"polalot-iep","src":"config/polalot-cfg.json","srcurl":"https://usmtf.specchain.org/polalot/file/config","path":"config/polalot-cfg.json","description":"POLALOT XML Information Exchange Package"},{"title":"REPOL","name":"repol-iep","src":"config/repol-cfg.json","srcurl":"https://usmtf.specchain.org/repol/file/config","path":"config/repol-cfg.json","description":"REPOL XML Information Exchange Package"},{"title":"POLRQMT","name":"polrqmt-iep","src":"config/polrqmt-cfg.json","srcurl":"https://usmtf.specchain.org/polrqmt/file/config","path":"config/polrqmt-cfg.json","description":"POLRQMT XML Information Exchange Package"},{"title":"CBRN1BIO","name":"cbrn1bio-iep","src":"config/cbrn1bio-cfg.json","srcurl":"https://usmtf.specchain.org/cbrn1bio/file/config","path":"config/cbrn1bio-cfg.json","description":"CBRN1BIO XML Information Exchange Package"},{"title":"CBRN1CHEM","name":"cbrn1chem-iep","src":"config/cbrn1chem-cfg.json","srcurl":"https://usmtf.specchain.org/cbrn1chem/file/config","path":"config/cbrn1chem-cfg.json","description":"CBRN1CHEM XML Information Exchange Package"},{"title":"CBRN1NUC","name":"cbrn1nuc-iep","src":"config/cbrn1nuc-cfg.json","srcurl":"https://usmtf.specchain.org/cbrn1nuc/file/config","path":"config/cbrn1nuc-cfg.json","description":"CBRN1NUC XML Information Exchange Package"},{"title":"CBRN1RAD","name":"cbrn1rad-iep","src":"config/cbrn1rad-cfg.json","srcurl":"https://usmtf.specchain.org/cbrn1rad/file/config","path":"config/cbrn1rad-cfg.json","description":"CBRN1RAD XML Information Exchange Package"},{"title":"CBRN2BIO","name":"cbrn2bio-iep","src":"config/cbrn2bio-cfg.json","srcurl":"https://usmtf.specchain.org/cbrn2bio/file/config","path":"config/cbrn2bio-cfg.json","description":"CBRN2BIO XML Information Exchange Package"},{"title":"CBRN2CHEM","name":"cbrn2chem-iep","src":"config/cbrn2chem-cfg.json","srcurl":"https://usmtf.specchain.org/cbrn2chem/file/config","path":"config/cbrn2chem-cfg.json","description":"CBRN2CHEM XML Information Exchange Package"},{"title":"CBRN2NUC","name":"cbrn2nuc-iep","src":"config/cbrn2nuc-cfg.json","srcurl":"https://usmtf.specchain.org/cbrn2nuc/file/config","path":"config/cbrn2nuc-cfg.json","description":"CBRN2NUC XML Information Exchange Package"},{"title":"CBRN2RAD","name":"cbrn2rad-iep","src":"config/cbrn2rad-cfg.json","srcurl":"https://usmtf.specchain.org/cbrn2rad/file/config","path":"config/cbrn2rad-cfg.json","description":"CBRN2RAD XML Information Exchange Package"},{"title":"CBRN3BIO","name":"cbrn3bio-iep","src":"config/cbrn3bio-cfg.json","srcurl":"https://usmtf.specchain.org/cbrn3bio/file/config","path":"config/cbrn3bio-cfg.json","description":"CBRN3BIO XML Information Exchange Package"},{"title":"CBRN3CHEM","name":"cbrn3chem-iep","src":"config/cbrn3chem-cfg.json","srcurl":"https://usmtf.specchain.org/cbrn3chem/file/config","path":"config/cbrn3chem-cfg.json","description":"CBRN3CHEM XML Information Exchange Package"},{"title":"CBRN3NUC","name":"cbrn3nuc-iep","src":"config/cbrn3nuc-cfg.json","srcurl":"https://usmtf.specchain.org/cbrn3nuc/file/config","path":"config/cbrn3nuc-cfg.json","description":"CBRN3NUC XML Information Exchange Package"},{"title":"CBRN3RAD","name":"cbrn3rad-iep","src":"config/cbrn3rad-cfg.json","srcurl":"https://usmtf.specchain.org/cbrn3rad/file/config","path":"config/cbrn3rad-cfg.json","description":"CBRN3RAD XML Information Exchange Package"},{"title":"CBRN4BIO","name":"cbrn4bio-iep","src":"config/cbrn4bio-cfg.json","srcurl":"https://usmtf.specchain.org/cbrn4bio/file/config","path":"config/cbrn4bio-cfg.json","description":"CBRN4BIO XML Information Exchange Package"},{"title":"CBRN4CHEM","name":"cbrn4chem-iep","src":"config/cbrn4chem-cfg.json","srcurl":"https://usmtf.specchain.org/cbrn4chem/file/config","path":"config/cbrn4chem-cfg.json","description":"CBRN4CHEM XML Information Exchange Package"},{"title":"CBRN4NUC","name":"cbrn4nuc-iep","src":"config/cbrn4nuc-cfg.json","srcurl":"https://usmtf.specchain.org/cbrn4nuc/file/config","path":"config/cbrn4nuc-cfg.json","description":"CBRN4NUC XML Information Exchange Package"},{"title":"CBRN4RAD","name":"cbrn4rad-iep","src":"config/cbrn4rad-cfg.json","srcurl":"https://usmtf.specchain.org/cbrn4rad/file/config","path":"config/cbrn4rad-cfg.json","description":"CBRN4RAD XML Information Exchange Package"},{"title":"CBRN5BIO","name":"cbrn5bio-iep","src":"config/cbrn5bio-cfg.json","srcurl":"https://usmtf.specchain.org/cbrn5bio/file/config","path":"config/cbrn5bio-cfg.json","description":"CBRN5BIO XML Information Exchange Package"},{"title":"CBRN5CHEM","name":"cbrn5chem-iep","src":"config/cbrn5chem-cfg.json","srcurl":"https://usmtf.specchain.org/cbrn5chem/file/config","path":"config/cbrn5chem-cfg.json","description":"CBRN5CHEM XML Information Exchange Package"},{"title":"CBRN5NUC","name":"cbrn5nuc-iep","src":"config/cbrn5nuc-cfg.json","srcurl":"https://usmtf.specchain.org/cbrn5nuc/file/config","path":"config/cbrn5nuc-cfg.json","description":"CBRN5NUC XML Information Exchange Package"},{"title":"CBRN5RAD","name":"cbrn5rad-iep","src":"config/cbrn5rad-cfg.json","srcurl":"https://usmtf.specchain.org/cbrn5rad/file/config","path":"config/cbrn5rad-cfg.json","description":"CBRN5RAD XML Information Exchange Package"},{"title":"CBRN6BIO","name":"cbrn6bio-iep","src":"config/cbrn6bio-cfg.json","srcurl":"https://usmtf.specchain.org/cbrn6bio/file/config","path":"config/cbrn6bio-cfg.json","description":"CBRN6BIO XML Information Exchange Package"},{"title":"CBRN6CHEM","name":"cbrn6chem-iep","src":"config/cbrn6chem-cfg.json","srcurl":"https://usmtf.specchain.org/cbrn6chem/file/config","path":"config/cbrn6chem-cfg.json","description":"CBRN6CHEM XML Information Exchange Package"},{"title":"CBRN6NUC","name":"cbrn6nuc-iep","src":"config/cbrn6nuc-cfg.json","srcurl":"https://usmtf.specchain.org/cbrn6nuc/file/config","path":"config/cbrn6nuc-cfg.json","description":"CBRN6NUC XML Information Exchange Package"},{"title":"CBRN6RAD","name":"cbrn6rad-iep","src":"config/cbrn6rad-cfg.json","srcurl":"https://usmtf.specchain.org/cbrn6rad/file/config","path":"config/cbrn6rad-cfg.json","description":"CBRN6RAD XML Information Exchange Package"},{"title":"CBRNBWR","name":"cbrnbwr-iep","src":"config/cbrnbwr-cfg.json","srcurl":"https://usmtf.specchain.org/cbrnbwr/file/config","path":"config/cbrnbwr-cfg.json","description":"CBRNBWR XML Information Exchange Package"},{"title":"CBRNCDR","name":"cbrncdr-iep","src":"config/cbrncdr-cfg.json","srcurl":"https://usmtf.specchain.org/cbrncdr/file/config","path":"config/cbrncdr-cfg.json","description":"CBRNCDR XML Information Exchange Package"},{"title":"CBRNEDR","name":"cbrnedr-iep","src":"config/cbrnedr-cfg.json","srcurl":"https://usmtf.specchain.org/cbrnedr/file/config","path":"config/cbrnedr-cfg.json","description":"CBRNEDR XML Information Exchange Package"},{"title":"CBRNHAZWARN","name":"cbrnhazwarn-iep","src":"config/cbrnhazwarn-cfg.json","srcurl":"https://usmtf.specchain.org/cbrnhazwarn/file/config","path":"config/cbrnhazwarn-cfg.json","description":"CBRNHAZWARN XML Information Exchange Package"},{"title":"CBRNMIR","name":"cbrnmir-iep","src":"config/cbrnmir-cfg.json","srcurl":"https://usmtf.specchain.org/cbrnmir/file/config","path":"config/cbrnmir-cfg.json","description":"CBRNMIR XML Information Exchange Package"},{"title":"CBRNSITREP","name":"cbrnsitrep-iep","src":"config/cbrnsitrep-cfg.json","srcurl":"https://usmtf.specchain.org/cbrnsitrep/file/config","path":"config/cbrnsitrep-cfg.json","description":"CBRNSITREP XML Information Exchange Package"},{"title":"CEMSTAT","name":"cemstat-iep","src":"config/cemstat-cfg.json","srcurl":"https://usmtf.specchain.org/cemstat/file/config","path":"config/cemstat-cfg.json","description":"CEMSTAT XML Information Exchange Package"},{"title":"CIVMILSTAT","name":"civmilstat-iep","src":"config/civmilstat-cfg.json","srcurl":"https://usmtf.specchain.org/civmilstat/file/config","path":"config/civmilstat-cfg.json","description":"CIVMILSTAT XML Information Exchange Package"},{"title":"CASSUM","name":"cassum-iep","src":"config/cassum-cfg.json","srcurl":"https://usmtf.specchain.org/cassum/file/config","path":"config/cassum-cfg.json","description":"CASSUM XML Information Exchange Package"},{"title":"CLB","name":"clb-iep","src":"config/clb-cfg.json","srcurl":"https://usmtf.specchain.org/clb/file/config","path":"config/clb-cfg.json","description":"CLB XML Information Exchange Package"},{"title":"COLLECTIVE","name":"collective-iep","src":"config/collective-cfg.json","srcurl":"https://usmtf.specchain.org/collective/file/config","path":"config/collective-cfg.json","description":"COLLECTIVE XML Information Exchange Package"},{"title":"CDRESTIMATE","name":"cdrestimate-iep","src":"config/cdrestimate-cfg.json","srcurl":"https://usmtf.specchain.org/cdrestimate/file/config","path":"config/cdrestimate-cfg.json","description":"CDRESTIMATE XML Information Exchange Package"},{"title":"CDREVALREQ","name":"cdrevalreq-iep","src":"config/cdrevalreq-cfg.json","srcurl":"https://usmtf.specchain.org/cdrevalreq/file/config","path":"config/cdrevalreq-cfg.json","description":"CDREVALREQ XML Information Exchange Package"},{"title":"SITREP","name":"sitrep-iep","src":"config/sitrep-cfg.json","srcurl":"https://usmtf.specchain.org/sitrep/file/config","path":"config/sitrep-cfg.json","description":"SITREP XML Information Exchange Package"},{"title":"COMM-EQUIPSTAT","name":"comm-equipstat-iep","src":"config/comm-equipstat-cfg.json","srcurl":"https://usmtf.specchain.org/comm-equipstat/file/config","path":"config/comm-equipstat-cfg.json","description":"COMM-EQUIPSTAT XML Information Exchange Package"},{"title":"COMMGRDLST","name":"commgrdlst-iep","src":"config/commgrdlst-cfg.json","srcurl":"https://usmtf.specchain.org/commgrdlst/file/config","path":"config/commgrdlst-cfg.json","description":"COMMGRDLST XML Information Exchange Package"},{"title":"COMMSHIFT","name":"commshift-iep","src":"config/commshift-cfg.json","srcurl":"https://usmtf.specchain.org/commshift/file/config","path":"config/commshift-cfg.json","description":"COMMSHIFT XML Information Exchange Package"},{"title":"COMSPOT","name":"comspot-iep","src":"config/comspot-cfg.json","srcurl":"https://usmtf.specchain.org/comspot/file/config","path":"config/comspot-cfg.json","description":"COMSPOT XML Information Exchange Package"},{"title":"COMTRAFICSUM","name":"comtraficsum-iep","src":"config/comtraficsum-cfg.json","srcurl":"https://usmtf.specchain.org/comtraficsum/file/config","path":"config/comtraficsum-cfg.json","description":"COMTRAFICSUM XML Information Exchange Package"},{"title":"CIHSR","name":"cihsr-iep","src":"config/cihsr-cfg.json","srcurl":"https://usmtf.specchain.org/cihsr/file/config","path":"config/cihsr-cfg.json","description":"CIHSR XML Information Exchange Package"},{"title":"CIIR","name":"ciir-iep","src":"config/ciir-cfg.json","srcurl":"https://usmtf.specchain.org/ciir/file/config","path":"config/ciir-cfg.json","description":"CIIR XML Information Exchange Package"},{"title":"COAEVALRESP","name":"coaevalresp-iep","src":"config/coaevalresp-cfg.json","srcurl":"https://usmtf.specchain.org/coaevalresp/file/config","path":"config/coaevalresp-cfg.json","description":"COAEVALRESP XML Information Exchange Package"},{"title":"CATASADVISORY","name":"catasadvisory-iep","src":"config/catasadvisory-cfg.json","srcurl":"https://usmtf.specchain.org/catasadvisory/file/config","path":"config/catasadvisory-cfg.json","description":"CATASADVISORY XML Information Exchange Package"},{"title":"CAL","name":"cal-iep","src":"config/cal-cfg.json","srcurl":"https://usmtf.specchain.org/cal/file/config","path":"config/cal-cfg.json","description":"CAL XML Information Exchange Package"},{"title":"DISUM","name":"disum-iep","src":"config/disum-cfg.json","srcurl":"https://usmtf.specchain.org/disum/file/config","path":"config/disum-cfg.json","description":"DISUM XML Information Exchange Package"},{"title":"DEPREP","name":"deprep-iep","src":"config/deprep-cfg.json","srcurl":"https://usmtf.specchain.org/deprep/file/config","path":"config/deprep-cfg.json","description":"DEPREP XML Information Exchange Package"},{"title":"DPZONE","name":"dpzone-iep","src":"config/dpzone-cfg.json","srcurl":"https://usmtf.specchain.org/dpzone/file/config","path":"config/dpzone-cfg.json","description":"DPZONE XML Information Exchange Package"},{"title":"EWAM","name":"ewam-iep","src":"config/ewam-cfg.json","srcurl":"https://usmtf.specchain.org/ewam/file/config","path":"config/ewam-cfg.json","description":"EWAM XML Information Exchange Package"},{"title":"EWEM","name":"ewem-iep","src":"config/ewem-cfg.json","srcurl":"https://usmtf.specchain.org/ewem/file/config","path":"config/ewem-cfg.json","description":"EWEM XML Information Exchange Package"},{"title":"EWDECONFLICT","name":"ewdeconflict-iep","src":"config/ewdeconflict-cfg.json","srcurl":"https://usmtf.specchain.org/ewdeconflict/file/config","path":"config/ewdeconflict-cfg.json","description":"EWDECONFLICT XML Information Exchange Package"},{"title":"EWMSNSUM","name":"ewmsnsum-iep","src":"config/ewmsnsum-cfg.json","srcurl":"https://usmtf.specchain.org/ewmsnsum/file/config","path":"config/ewmsnsum-cfg.json","description":"EWMSNSUM XML Information Exchange Package"},{"title":"EWRTM","name":"ewrtm-iep","src":"config/ewrtm-cfg.json","srcurl":"https://usmtf.specchain.org/ewrtm/file/config","path":"config/ewrtm-cfg.json","description":"EWRTM XML Information Exchange Package"},{"title":"ENACTWPN","name":"enactwpn-iep","src":"config/enactwpn-cfg.json","srcurl":"https://usmtf.specchain.org/enactwpn/file/config","path":"config/enactwpn-cfg.json","description":"ENACTWPN XML Information Exchange Package"},{"title":"EOBSREP","name":"eobsrep-iep","src":"config/eobsrep-cfg.json","srcurl":"https://usmtf.specchain.org/eobsrep/file/config","path":"config/eobsrep-cfg.json","description":"EOBSREP XML Information Exchange Package"},{"title":"EPWSTAT","name":"epwstat-iep","src":"config/epwstat-cfg.json","srcurl":"https://usmtf.specchain.org/epwstat/file/config","path":"config/epwstat-cfg.json","description":"EPWSTAT XML Information Exchange Package"},{"title":"ENSIT","name":"ensit-iep","src":"config/ensit-cfg.json","srcurl":"https://usmtf.specchain.org/ensit/file/config","path":"config/ensit-cfg.json","description":"ENSIT XML Information Exchange Package"},{"title":"CASREP","name":"casrep-iep","src":"config/casrep-cfg.json","srcurl":"https://usmtf.specchain.org/casrep/file/config","path":"config/casrep-cfg.json","description":"CASREP XML Information Exchange Package"},{"title":"PORT","name":"port-iep","src":"config/port-cfg.json","srcurl":"https://usmtf.specchain.org/port/file/config","path":"config/port-cfg.json","description":"PORT XML Information Exchange Package"},{"title":"EODSPT","name":"eodspt-iep","src":"config/eodspt-cfg.json","srcurl":"https://usmtf.specchain.org/eodspt/file/config","path":"config/eodspt-cfg.json","description":"EODSPT XML Information Exchange Package"},{"title":"FMCFF","name":"fmcff-iep","src":"config/fmcff-cfg.json","srcurl":"https://usmtf.specchain.org/fmcff/file/config","path":"config/fmcff-cfg.json","description":"FMCFF XML Information Exchange Package"},{"title":"FMFMC","name":"fmfmc-iep","src":"config/fmfmc-cfg.json","srcurl":"https://usmtf.specchain.org/fmfmc/file/config","path":"config/fmfmc-cfg.json","description":"FMFMC XML Information Exchange Package"},{"title":"FMMTO","name":"fmmto-iep","src":"config/fmmto-cfg.json","srcurl":"https://usmtf.specchain.org/fmmto/file/config","path":"config/fmmto-cfg.json","description":"FMMTO XML Information Exchange Package"},{"title":"FMNCF","name":"fmncf-iep","src":"config/fmncf-cfg.json","srcurl":"https://usmtf.specchain.org/fmncf/file/config","path":"config/fmncf-cfg.json","description":"FMNCF XML Information Exchange Package"},{"title":"FMSUB","name":"fmsub-iep","src":"config/fmsub-cfg.json","srcurl":"https://usmtf.specchain.org/fmsub/file/config","path":"config/fmsub-cfg.json","description":"FMSUB XML Information Exchange Package"},{"title":"FPATL","name":"fpatl-iep","src":"config/fpatl-cfg.json","srcurl":"https://usmtf.specchain.org/fpatl/file/config","path":"config/fpatl-cfg.json","description":"FPATL XML Information Exchange Package"},{"title":"FPCOMPFP","name":"fpcompfp-iep","src":"config/fpcompfp-cfg.json","srcurl":"https://usmtf.specchain.org/fpcompfp/file/config","path":"config/fpcompfp-cfg.json","description":"FPCOMPFP XML Information Exchange Package"},{"title":"FPFPT","name":"fpfpt-iep","src":"config/fpfpt-cfg.json","srcurl":"https://usmtf.specchain.org/fpfpt/file/config","path":"config/fpfpt-cfg.json","description":"FPFPT XML Information Exchange Package"},{"title":"FPNUCSCD","name":"fpnucscd-iep","src":"config/fpnucscd-cfg.json","srcurl":"https://usmtf.specchain.org/fpnucscd/file/config","path":"config/fpnucscd-cfg.json","description":"FPNUCSCD XML Information Exchange Package"},{"title":"FPRESFU","name":"fpresfu-iep","src":"config/fpresfu-cfg.json","srcurl":"https://usmtf.specchain.org/fpresfu/file/config","path":"config/fpresfu-cfg.json","description":"FPRESFU XML Information Exchange Package"},{"title":"FSEFRD","name":"fsefrd-iep","src":"config/fsefrd-cfg.json","srcurl":"https://usmtf.specchain.org/fsefrd/file/config","path":"config/fsefrd-cfg.json","description":"FSEFRD XML Information Exchange Package"},{"title":"FSEALLOC","name":"fsealloc-iep","src":"config/fsealloc-cfg.json","srcurl":"https://usmtf.specchain.org/fsealloc/file/config","path":"config/fsealloc-cfg.json","description":"FSEALLOC XML Information Exchange Package"},{"title":"FIRESUPREQ","name":"firesupreq-iep","src":"config/firesupreq-cfg.json","srcurl":"https://usmtf.specchain.org/firesupreq/file/config","path":"config/firesupreq-cfg.json","description":"FIRESUPREQ XML Information Exchange Package"},{"title":"FLTCONTINFO","name":"fltcontinfo-iep","src":"config/fltcontinfo-cfg.json","srcurl":"https://usmtf.specchain.org/fltcontinfo/file/config","path":"config/fltcontinfo-cfg.json","description":"FLTCONTINFO XML Information Exchange Package"},{"title":"GENADMIN","name":"genadmin-iep","src":"config/genadmin-cfg.json","srcurl":"https://usmtf.specchain.org/genadmin/file/config","path":"config/genadmin-cfg.json","description":"GENADMIN XML Information Exchange Package"},{"title":"GMFACCESSAUTH","name":"gmfaccessauth-iep","src":"config/gmfaccessauth-cfg.json","srcurl":"https://usmtf.specchain.org/gmfaccessauth/file/config","path":"config/gmfaccessauth-cfg.json","description":"GMFACCESSAUTH XML Information Exchange Package"},{"title":"GMFDENIAL","name":"gmfdenial-iep","src":"config/gmfdenial-cfg.json","srcurl":"https://usmtf.specchain.org/gmfdenial/file/config","path":"config/gmfdenial-cfg.json","description":"GMFDENIAL XML Information Exchange Package"},{"title":"GMFACCESSREQ","name":"gmfaccessreq-iep","src":"config/gmfaccessreq-cfg.json","srcurl":"https://usmtf.specchain.org/gmfaccessreq/file/config","path":"config/gmfaccessreq-cfg.json","description":"GMFACCESSREQ XML Information Exchange Package"},{"title":"GMFCANCREQ","name":"gmfcancreq-iep","src":"config/gmfcancreq-cfg.json","srcurl":"https://usmtf.specchain.org/gmfcancreq/file/config","path":"config/gmfcancreq-cfg.json","description":"GMFCANCREQ XML Information Exchange Package"},{"title":"GRAPHREP-OVERLAY","name":"graphrep-overlay-iep","src":"config/graphrep-overlay-cfg.json","srcurl":"https://usmtf.specchain.org/graphrep-overlay/file/config","path":"config/graphrep-overlay-cfg.json","description":"GRAPHREP-OVERLAY XML Information Exchange Package"},{"title":"HLA","name":"hla-iep","src":"config/hla-cfg.json","srcurl":"https://usmtf.specchain.org/hla/file/config","path":"config/hla-cfg.json","description":"HLA XML Information Exchange Package"},{"title":"HWYSITREP","name":"hwysitrep-iep","src":"config/hwysitrep-cfg.json","srcurl":"https://usmtf.specchain.org/hwysitrep/file/config","path":"config/hwysitrep-cfg.json","description":"HWYSITREP XML Information Exchange Package"},{"title":"REMAINSARSTAT","name":"remainsarstat-iep","src":"config/remainsarstat-cfg.json","srcurl":"https://usmtf.specchain.org/remainsarstat/file/config","path":"config/remainsarstat-cfg.json","description":"REMAINSARSTAT XML Information Exchange Package"},{"title":"IIR","name":"iir-iep","src":"config/iir-cfg.json","srcurl":"https://usmtf.specchain.org/iir/file/config","path":"config/iir-cfg.json","description":"IIR XML Information Exchange Package"},{"title":"INFLIGHTREP","name":"inflightrep-iep","src":"config/inflightrep-cfg.json","srcurl":"https://usmtf.specchain.org/inflightrep/file/config","path":"config/inflightrep-cfg.json","description":"INFLIGHTREP XML Information Exchange Package"},{"title":"INTREP","name":"intrep-iep","src":"config/intrep-cfg.json","srcurl":"https://usmtf.specchain.org/intrep/file/config","path":"config/intrep-cfg.json","description":"INTREP XML Information Exchange Package"},{"title":"INTELSITSUM","name":"intelsitsum-iep","src":"config/intelsitsum-cfg.json","srcurl":"https://usmtf.specchain.org/intelsitsum/file/config","path":"config/intelsitsum-cfg.json","description":"INTELSITSUM XML Information Exchange Package"},{"title":"INTSUM","name":"intsum-iep","src":"config/intsum-cfg.json","srcurl":"https://usmtf.specchain.org/intsum/file/config","path":"config/intsum-cfg.json","description":"INTSUM XML Information Exchange Package"},{"title":"INTERDICTION","name":"interdiction-iep","src":"config/interdiction-cfg.json","srcurl":"https://usmtf.specchain.org/interdiction/file/config","path":"config/interdiction-cfg.json","description":"INTERDICTION XML Information Exchange Package"},{"title":"JAMWARN","name":"jamwarn-iep","src":"config/jamwarn-cfg.json","srcurl":"https://usmtf.specchain.org/jamwarn/file/config","path":"config/jamwarn-cfg.json","description":"JAMWARN XML Information Exchange Package"},{"title":"JAREVENT","name":"jarevent-iep","src":"config/jarevent-cfg.json","srcurl":"https://usmtf.specchain.org/jarevent/file/config","path":"config/jarevent-cfg.json","description":"JAREVENT XML Information Exchange Package"},{"title":"JARTRACK","name":"jartrack-iep","src":"config/jartrack-cfg.json","srcurl":"https://usmtf.specchain.org/jartrack/file/config","path":"config/jartrack-cfg.json","description":"JARTRACK XML Information Exchange Package"},{"title":"JALSCD","name":"jalscd-iep","src":"config/jalscd-cfg.json","srcurl":"https://usmtf.specchain.org/jalscd/file/config","path":"config/jalscd-cfg.json","description":"JALSCD XML Information Exchange Package"},{"title":"JALDIP","name":"jaldip-iep","src":"config/jaldip-cfg.json","srcurl":"https://usmtf.specchain.org/jaldip/file/config","path":"config/jaldip-cfg.json","description":"JALDIP XML Information Exchange Package"},{"title":"JALHMNRMS","name":"jalhmnrms-iep","src":"config/jalhmnrms-cfg.json","srcurl":"https://usmtf.specchain.org/jalhmnrms/file/config","path":"config/jalhmnrms-cfg.json","description":"JALHMNRMS XML Information Exchange Package"},{"title":"JALADV","name":"jaladv-iep","src":"config/jaladv-cfg.json","srcurl":"https://usmtf.specchain.org/jaladv/file/config","path":"config/jaladv-cfg.json","description":"JALADV XML Information Exchange Package"},{"title":"JALARR","name":"jalarr-iep","src":"config/jalarr-cfg.json","srcurl":"https://usmtf.specchain.org/jalarr/file/config","path":"config/jalarr-cfg.json","description":"JALARR XML Information Exchange Package"},{"title":"JALDEP","name":"jaldep-iep","src":"config/jaldep-cfg.json","srcurl":"https://usmtf.specchain.org/jaldep/file/config","path":"config/jaldep-cfg.json","description":"JALDEP XML Information Exchange Package"},{"title":"JALLOAD","name":"jalload-iep","src":"config/jalload-cfg.json","srcurl":"https://usmtf.specchain.org/jalload/file/config","path":"config/jalload-cfg.json","description":"JALLOAD XML Information Exchange Package"},{"title":"JALRPTREQ","name":"jalrptreq-iep","src":"config/jalrptreq-cfg.json","srcurl":"https://usmtf.specchain.org/jalrptreq/file/config","path":"config/jalrptreq-cfg.json","description":"JALRPTREQ XML Information Exchange Package"},{"title":"JALSCDREQ","name":"jalscdreq-iep","src":"config/jalscdreq-cfg.json","srcurl":"https://usmtf.specchain.org/jalscdreq/file/config","path":"config/jalscdreq-cfg.json","description":"JALSCDREQ XML Information Exchange Package"},{"title":"JSYSREJECT","name":"jsysreject-iep","src":"config/jsysreject-cfg.json","srcurl":"https://usmtf.specchain.org/jsysreject/file/config","path":"config/jsysreject-cfg.json","description":"JSYSREJECT XML Information Exchange Package"},{"title":"JCRMK","name":"jcrmk-iep","src":"config/jcrmk-cfg.json","srcurl":"https://usmtf.specchain.org/jcrmk/file/config","path":"config/jcrmk-cfg.json","description":"JCRMK XML Information Exchange Package"},{"title":"JCREWSTAT","name":"jcrewstat-iep","src":"config/jcrewstat-cfg.json","srcurl":"https://usmtf.specchain.org/jcrewstat/file/config","path":"config/jcrewstat-cfg.json","description":"JCREWSTAT XML Information Exchange Package"},{"title":"JLMCMWOPS","name":"jlmcmwops-iep","src":"config/jlmcmwops-cfg.json","srcurl":"https://usmtf.specchain.org/jlmcmwops/file/config","path":"config/jlmcmwops-cfg.json","description":"JLMCMWOPS XML Information Exchange Package"},{"title":"JLMINWOPS","name":"jlminwops-iep","src":"config/jlminwops-cfg.json","srcurl":"https://usmtf.specchain.org/jlminwops/file/config","path":"config/jlminwops-cfg.json","description":"JLMINWOPS XML Information Exchange Package"},{"title":"JLNCHREP","name":"jlnchrep-iep","src":"config/jlnchrep-cfg.json","srcurl":"https://usmtf.specchain.org/jlnchrep/file/config","path":"config/jlnchrep-cfg.json","description":"JLNCHREP XML Information Exchange Package"},{"title":"JALMXASSIST","name":"jalmxassist-iep","src":"config/jalmxassist-cfg.json","srcurl":"https://usmtf.specchain.org/jalmxassist/file/config","path":"config/jalmxassist-cfg.json","description":"JALMXASSIST XML Information Exchange Package"},{"title":"JALMXSTAT","name":"jalmxstat-iep","src":"config/jalmxstat-cfg.json","srcurl":"https://usmtf.specchain.org/jalmxstat/file/config","path":"config/jalmxstat-cfg.json","description":"JALMXSTAT XML Information Exchange Package"},{"title":"JMSNSTAT","name":"jmsnstat-iep","src":"config/jmsnstat-cfg.json","srcurl":"https://usmtf.specchain.org/jmsnstat/file/config","path":"config/jmsnstat-cfg.json","description":"JMSNSTAT XML Information Exchange Package"},{"title":"JRSR","name":"jrsr-iep","src":"config/jrsr-cfg.json","srcurl":"https://usmtf.specchain.org/jrsr/file/config","path":"config/jrsr-cfg.json","description":"JRSR XML Information Exchange Package"},{"title":"JADREPD","name":"jadrepd-iep","src":"config/jadrepd-cfg.json","srcurl":"https://usmtf.specchain.org/jadrepd/file/config","path":"config/jadrepd-cfg.json","description":"JADREPD XML Information Exchange Package"},{"title":"SHIPSERREQ","name":"shipserreq-iep","src":"config/shipserreq-cfg.json","srcurl":"https://usmtf.specchain.org/shipserreq/file/config","path":"config/shipserreq-cfg.json","description":"SHIPSERREQ XML Information Exchange Package"},{"title":"JASGNTAIL","name":"jasgntail-iep","src":"config/jasgntail-cfg.json","srcurl":"https://usmtf.specchain.org/jasgntail/file/config","path":"config/jasgntail-cfg.json","description":"JASGNTAIL XML Information Exchange Package"},{"title":"LSP","name":"lsp-iep","src":"config/lsp-cfg.json","srcurl":"https://usmtf.specchain.org/lsp/file/config","path":"config/lsp-cfg.json","description":"LSP XML Information Exchange Package"},{"title":"LOC","name":"loc-iep","src":"config/loc-cfg.json","srcurl":"https://usmtf.specchain.org/loc/file/config","path":"config/loc-cfg.json","description":"LOC XML Information Exchange Package"},{"title":"LOGSITLAND(PEACE)","name":"logsitland(peace)-iep","src":"config/logsitland(peace)-cfg.json","srcurl":"https://usmtf.specchain.org/logsitland(peace)/file/config","path":"config/logsitland(peace)-cfg.json","description":"LOGSITLAND(PEACE) XML Information Exchange Package"},{"title":"LOGSITREP","name":"logsitrep-iep","src":"config/logsitrep-cfg.json","srcurl":"https://usmtf.specchain.org/logsitrep/file/config","path":"config/logsitrep-cfg.json","description":"LOGSITREP XML Information Exchange Package"},{"title":"MAILDISTCH","name":"maildistch-iep","src":"config/maildistch-cfg.json","srcurl":"https://usmtf.specchain.org/maildistch/file/config","path":"config/maildistch-cfg.json","description":"MAILDISTCH XML Information Exchange Package"},{"title":"MAINTSPTREQ","name":"maintsptreq-iep","src":"config/maintsptreq-cfg.json","srcurl":"https://usmtf.specchain.org/maintsptreq/file/config","path":"config/maintsptreq-cfg.json","description":"MAINTSPTREQ XML Information Exchange Package"},{"title":"MAINTSPTRES","name":"maintsptres-iep","src":"config/maintsptres-cfg.json","srcurl":"https://usmtf.specchain.org/maintsptres/file/config","path":"config/maintsptres-cfg.json","description":"MAINTSPTRES XML Information Exchange Package"},{"title":"AMMOMALFUNCREP","name":"ammomalfuncrep-iep","src":"config/ammomalfuncrep-cfg.json","srcurl":"https://usmtf.specchain.org/ammomalfuncrep/file/config","path":"config/ammomalfuncrep-cfg.json","description":"AMMOMALFUNCREP XML Information Exchange Package"},{"title":"TURQUOISEDEVIATION","name":"turquoisedeviation-iep","src":"config/turquoisedeviation-cfg.json","srcurl":"https://usmtf.specchain.org/turquoisedeviation/file/config","path":"config/turquoisedeviation-cfg.json","description":"TURQUOISEDEVIATION XML Information Exchange Package"},{"title":"TURQUOISEREPORT","name":"turquoisereport-iep","src":"config/turquoisereport-cfg.json","srcurl":"https://usmtf.specchain.org/turquoisereport/file/config","path":"config/turquoisereport-cfg.json","description":"TURQUOISEREPORT XML Information Exchange Package"},{"title":"LOCATOR","name":"locator-iep","src":"config/locator-cfg.json","srcurl":"https://usmtf.specchain.org/locator/file/config","path":"config/locator-cfg.json","description":"LOCATOR XML Information Exchange Package"},{"title":"MARINTREP","name":"marintrep-iep","src":"config/marintrep-cfg.json","srcurl":"https://usmtf.specchain.org/marintrep/file/config","path":"config/marintrep-cfg.json","description":"MARINTREP XML Information Exchange Package"},{"title":"MARINTSUM","name":"marintsum-iep","src":"config/marintsum-cfg.json","srcurl":"https://usmtf.specchain.org/marintsum/file/config","path":"config/marintsum-cfg.json","description":"MARINTSUM XML Information Exchange Package"},{"title":"PURPLE","name":"purple-iep","src":"config/purple-cfg.json","srcurl":"https://usmtf.specchain.org/purple/file/config","path":"config/purple-cfg.json","description":"PURPLE XML Information Exchange Package"},{"title":"INDIGOFIRINGREPORT","name":"indigofiringreport-iep","src":"config/indigofiringreport-cfg.json","srcurl":"https://usmtf.specchain.org/indigofiringreport/file/config","path":"config/indigofiringreport-cfg.json","description":"INDIGOFIRINGREPORT XML Information Exchange Package"},{"title":"TURQUOISE","name":"turquoise-iep","src":"config/turquoise-cfg.json","srcurl":"https://usmtf.specchain.org/turquoise/file/config","path":"config/turquoise-cfg.json","description":"TURQUOISE XML Information Exchange Package"},{"title":"TURQUOISEREQUEST","name":"turquoiserequest-iep","src":"config/turquoiserequest-cfg.json","srcurl":"https://usmtf.specchain.org/turquoiserequest/file/config","path":"config/turquoiserequest-cfg.json","description":"TURQUOISEREQUEST XML Information Exchange Package"},{"title":"GREEN","name":"green-iep","src":"config/green-cfg.json","srcurl":"https://usmtf.specchain.org/green/file/config","path":"config/green-cfg.json","description":"GREEN XML Information Exchange Package"},{"title":"INDIGO","name":"indigo-iep","src":"config/indigo-cfg.json","srcurl":"https://usmtf.specchain.org/indigo/file/config","path":"config/indigo-cfg.json","description":"INDIGO XML Information Exchange Package"},{"title":"MAR","name":"mar-iep","src":"config/mar-cfg.json","srcurl":"https://usmtf.specchain.org/mar/file/config","path":"config/mar-cfg.json","description":"MAR XML Information Exchange Package"},{"title":"MCMREP","name":"mcmrep-iep","src":"config/mcmrep-cfg.json","srcurl":"https://usmtf.specchain.org/mcmrep/file/config","path":"config/mcmrep-cfg.json","description":"MCMREP XML Information Exchange Package"},{"title":"OPTASKMCM","name":"optaskmcm-iep","src":"config/optaskmcm-cfg.json","srcurl":"https://usmtf.specchain.org/optaskmcm/file/config","path":"config/optaskmcm-cfg.json","description":"OPTASKMCM XML Information Exchange Package"},{"title":"MIJIFEEDER","name":"mijifeeder-iep","src":"config/mijifeeder-cfg.json","srcurl":"https://usmtf.specchain.org/mijifeeder/file/config","path":"config/mijifeeder-cfg.json","description":"MIJIFEEDER XML Information Exchange Package"},{"title":"MEDREGREP","name":"medregrep-iep","src":"config/medregrep-cfg.json","srcurl":"https://usmtf.specchain.org/medregrep/file/config","path":"config/medregrep-cfg.json","description":"MEDREGREP XML Information Exchange Package"},{"title":"MEDSTAT","name":"medstat-iep","src":"config/medstat-cfg.json","srcurl":"https://usmtf.specchain.org/medstat/file/config","path":"config/medstat-cfg.json","description":"MEDSTAT XML Information Exchange Package"},{"title":"MSGCORRCANX","name":"msgcorrcanx-iep","src":"config/msgcorrcanx-cfg.json","srcurl":"https://usmtf.specchain.org/msgcorrcanx/file/config","path":"config/msgcorrcanx-cfg.json","description":"MSGCORRCANX XML Information Exchange Package"},{"title":"METCM","name":"metcm-iep","src":"config/metcm-cfg.json","srcurl":"https://usmtf.specchain.org/metcm/file/config","path":"config/metcm-cfg.json","description":"METCM XML Information Exchange Package"},{"title":"METCF","name":"metcf-iep","src":"config/metcf-cfg.json","srcurl":"https://usmtf.specchain.org/metcf/file/config","path":"config/metcf-cfg.json","description":"METCF XML Information Exchange Package"},{"title":"METRFM","name":"metrfm-iep","src":"config/metrfm-cfg.json","srcurl":"https://usmtf.specchain.org/metrfm/file/config","path":"config/metrfm-cfg.json","description":"METRFM XML Information Exchange Package"},{"title":"METTA","name":"metta-iep","src":"config/metta-cfg.json","srcurl":"https://usmtf.specchain.org/metta/file/config","path":"config/metta-cfg.json","description":"METTA XML Information Exchange Package"},{"title":"POSTREQ","name":"postreq-iep","src":"config/postreq-cfg.json","srcurl":"https://usmtf.specchain.org/postreq/file/config","path":"config/postreq-cfg.json","description":"POSTREQ XML Information Exchange Package"},{"title":"ENVREP","name":"envrep-iep","src":"config/envrep-cfg.json","srcurl":"https://usmtf.specchain.org/envrep/file/config","path":"config/envrep-cfg.json","description":"ENVREP XML Information Exchange Package"},{"title":"MLAYREP","name":"mlayrep-iep","src":"config/mlayrep-cfg.json","srcurl":"https://usmtf.specchain.org/mlayrep/file/config","path":"config/mlayrep-cfg.json","description":"MLAYREP XML Information Exchange Package"},{"title":"OPTASKMINING","name":"optaskmining-iep","src":"config/optaskmining-cfg.json","srcurl":"https://usmtf.specchain.org/optaskmining/file/config","path":"config/optaskmining-cfg.json","description":"OPTASKMINING XML Information Exchange Package"},{"title":"MISREP","name":"misrep-iep","src":"config/misrep-cfg.json","srcurl":"https://usmtf.specchain.org/misrep/file/config","path":"config/misrep-cfg.json","description":"MISREP XML Information Exchange Package"},{"title":"MSR","name":"msr-iep","src":"config/msr-cfg.json","srcurl":"https://usmtf.specchain.org/msr/file/config","path":"config/msr-cfg.json","description":"MSR XML Information Exchange Package"},{"title":"MODATTACK","name":"modattack-iep","src":"config/modattack-cfg.json","srcurl":"https://usmtf.specchain.org/modattack/file/config","path":"config/modattack-cfg.json","description":"MODATTACK XML Information Exchange Package"},{"title":"MODXCLUDE","name":"modxclude-iep","src":"config/modxclude-cfg.json","srcurl":"https://usmtf.specchain.org/modxclude/file/config","path":"config/modxclude-cfg.json","description":"MODXCLUDE XML Information Exchange Package"},{"title":"MOVEREP","name":"moverep-iep","src":"config/moverep-cfg.json","srcurl":"https://usmtf.specchain.org/moverep/file/config","path":"config/moverep-cfg.json","description":"MOVEREP XML Information Exchange Package"},{"title":"MUREP","name":"murep-iep","src":"config/murep-cfg.json","srcurl":"https://usmtf.specchain.org/murep/file/config","path":"config/murep-cfg.json","description":"MUREP XML Information Exchange Package"},{"title":"NAVSITREP","name":"navsitrep-iep","src":"config/navsitrep-cfg.json","srcurl":"https://usmtf.specchain.org/navsitrep/file/config","path":"config/navsitrep-cfg.json","description":"NAVSITREP XML Information Exchange Package"},{"title":"NAVSITSUM","name":"navsitsum-iep","src":"config/navsitsum-cfg.json","srcurl":"https://usmtf.specchain.org/navsitsum/file/config","path":"config/navsitsum-cfg.json","description":"NAVSITSUM XML Information Exchange Package"},{"title":"NBC1SUM","name":"nbc1sum-iep","src":"config/nbc1sum-cfg.json","srcurl":"https://usmtf.specchain.org/nbc1sum/file/config","path":"config/nbc1sum-cfg.json","description":"NBC1SUM XML Information Exchange Package"},{"title":"NBC2SUM","name":"nbc2sum-iep","src":"config/nbc2sum-cfg.json","srcurl":"https://usmtf.specchain.org/nbc2sum/file/config","path":"config/nbc2sum-cfg.json","description":"NBC2SUM XML Information Exchange Package"},{"title":"STRIKWARN","name":"strikwarn-iep","src":"config/strikwarn-cfg.json","srcurl":"https://usmtf.specchain.org/strikwarn/file/config","path":"config/strikwarn-cfg.json","description":"STRIKWARN XML Information Exchange Package"},{"title":"OIXMOD","name":"oixmod-iep","src":"config/oixmod-cfg.json","srcurl":"https://usmtf.specchain.org/oixmod/file/config","path":"config/oixmod-cfg.json","description":"OIXMOD XML Information Exchange Package"},{"title":"GRASSHOPPEREXECUTE","name":"grasshopperexecute-iep","src":"config/grasshopperexecute-cfg.json","srcurl":"https://usmtf.specchain.org/grasshopperexecute/file/config","path":"config/grasshopperexecute-cfg.json","description":"GRASSHOPPEREXECUTE XML Information Exchange Package"},{"title":"GRASSHOPPERREQUEST","name":"grasshopperrequest-iep","src":"config/grasshopperrequest-cfg.json","srcurl":"https://usmtf.specchain.org/grasshopperrequest/file/config","path":"config/grasshopperrequest-cfg.json","description":"GRASSHOPPERREQUEST XML Information Exchange Package"},{"title":"OPGEN","name":"opgen-iep","src":"config/opgen-cfg.json","srcurl":"https://usmtf.specchain.org/opgen/file/config","path":"config/opgen-cfg.json","description":"OPGEN XML Information Exchange Package"},{"title":"OPSTATRAS","name":"opstatras-iep","src":"config/opstatras-cfg.json","srcurl":"https://usmtf.specchain.org/opstatras/file/config","path":"config/opstatras-cfg.json","description":"OPSTATRAS XML Information Exchange Package"},{"title":"OPSTATRASREQ","name":"opstatrasreq-iep","src":"config/opstatrasreq-cfg.json","srcurl":"https://usmtf.specchain.org/opstatrasreq/file/config","path":"config/opstatrasreq-cfg.json","description":"OPSTATRASREQ XML Information Exchange Package"},{"title":"OPSTATUNIT","name":"opstatunit-iep","src":"config/opstatunit-cfg.json","srcurl":"https://usmtf.specchain.org/opstatunit/file/config","path":"config/opstatunit-cfg.json","description":"OPSTATUNIT XML Information Exchange Package"},{"title":"OPTASKAAW","name":"optaskaaw-iep","src":"config/optaskaaw-cfg.json","srcurl":"https://usmtf.specchain.org/optaskaaw/file/config","path":"config/optaskaaw-cfg.json","description":"OPTASKAAW XML Information Exchange Package"},{"title":"OPTASKASW","name":"optaskasw-iep","src":"config/optaskasw-cfg.json","srcurl":"https://usmtf.specchain.org/optaskasw/file/config","path":"config/optaskasw-cfg.json","description":"OPTASKASW XML Information Exchange Package"},{"title":"OPTASKCOP-CTP","name":"optaskcop-ctp-iep","src":"config/optaskcop-ctp-cfg.json","srcurl":"https://usmtf.specchain.org/optaskcop-ctp/file/config","path":"config/optaskcop-ctp-cfg.json","description":"OPTASKCOP-CTP XML Information Exchange Package"},{"title":"OPTASKCOMMS","name":"optaskcomms-iep","src":"config/optaskcomms-cfg.json","srcurl":"https://usmtf.specchain.org/optaskcomms/file/config","path":"config/optaskcomms-cfg.json","description":"OPTASKCOMMS XML Information Exchange Package"},{"title":"OPTASKLINK","name":"optasklink-iep","src":"config/optasklink-cfg.json","srcurl":"https://usmtf.specchain.org/optasklink/file/config","path":"config/optasklink-cfg.json","description":"OPTASKLINK XML Information Exchange Package"},{"title":"OPTASKLINKIDSUPP","name":"optasklinkidsupp-iep","src":"config/optasklinkidsupp-cfg.json","srcurl":"https://usmtf.specchain.org/optasklinkidsupp/file/config","path":"config/optasklinkidsupp-cfg.json","description":"OPTASKLINKIDSUPP XML Information Exchange Package"},{"title":"OPTASKEW","name":"optaskew-iep","src":"config/optaskew-cfg.json","srcurl":"https://usmtf.specchain.org/optaskew/file/config","path":"config/optaskew-cfg.json","description":"OPTASKEW XML Information Exchange Package"},{"title":"OPTASKGENERAL","name":"optaskgeneral-iep","src":"config/optaskgeneral-cfg.json","srcurl":"https://usmtf.specchain.org/optaskgeneral/file/config","path":"config/optaskgeneral-cfg.json","description":"OPTASKGENERAL XML Information Exchange Package"},{"title":"OPTASKIM","name":"optaskim-iep","src":"config/optaskim-cfg.json","srcurl":"https://usmtf.specchain.org/optaskim/file/config","path":"config/optaskim-cfg.json","description":"OPTASKIM XML Information Exchange Package"},{"title":"OPTASKNUC","name":"optasknuc-iep","src":"config/optasknuc-cfg.json","srcurl":"https://usmtf.specchain.org/optasknuc/file/config","path":"config/optasknuc-cfg.json","description":"OPTASKNUC XML Information Exchange Package"},{"title":"OPTASKASUW","name":"optaskasuw-iep","src":"config/optaskasuw-cfg.json","srcurl":"https://usmtf.specchain.org/optaskasuw/file/config","path":"config/optaskasuw-cfg.json","description":"OPTASKASUW XML Information Exchange Package"},{"title":"OPTASKRAS","name":"optaskras-iep","src":"config/optaskras-cfg.json","srcurl":"https://usmtf.specchain.org/optaskras/file/config","path":"config/optaskras-cfg.json","description":"OPTASKRAS XML Information Exchange Package"},{"title":"PLANORDCHG","name":"planordchg-iep","src":"config/planordchg-cfg.json","srcurl":"https://usmtf.specchain.org/planordchg/file/config","path":"config/planordchg-cfg.json","description":"PLANORDCHG XML Information Exchange Package"},{"title":"OPSUM","name":"opsum-iep","src":"config/opsum-cfg.json","srcurl":"https://usmtf.specchain.org/opsum/file/config","path":"config/opsum-cfg.json","description":"OPSUM XML Information Exchange Package"},{"title":"OPREP-3","name":"oprep-3-iep","src":"config/oprep-3-cfg.json","srcurl":"https://usmtf.specchain.org/oprep-3/file/config","path":"config/oprep-3-cfg.json","description":"OPREP-3 XML Information Exchange Package"},{"title":"OPREP-3B","name":"oprep-3b-iep","src":"config/oprep-3b-cfg.json","srcurl":"https://usmtf.specchain.org/oprep-3b/file/config","path":"config/oprep-3b-cfg.json","description":"OPREP-3B XML Information Exchange Package"},{"title":"OPREP-3BS","name":"oprep-3bs-iep","src":"config/oprep-3bs-cfg.json","srcurl":"https://usmtf.specchain.org/oprep-3bs/file/config","path":"config/oprep-3bs-cfg.json","description":"OPREP-3BS XML Information Exchange Package"},{"title":"OPREP-3DS","name":"oprep-3ds-iep","src":"config/oprep-3ds-cfg.json","srcurl":"https://usmtf.specchain.org/oprep-3ds/file/config","path":"config/oprep-3ds-cfg.json","description":"OPREP-3DS XML Information Exchange Package"},{"title":"OPREP-3FG","name":"oprep-3fg-iep","src":"config/oprep-3fg-cfg.json","srcurl":"https://usmtf.specchain.org/oprep-3fg/file/config","path":"config/oprep-3fg-cfg.json","description":"OPREP-3FG XML Information Exchange Package"},{"title":"OPREP-3H","name":"oprep-3h-iep","src":"config/oprep-3h-cfg.json","srcurl":"https://usmtf.specchain.org/oprep-3h/file/config","path":"config/oprep-3h-cfg.json","description":"OPREP-3H XML Information Exchange Package"},{"title":"OPREP-3NB","name":"oprep-3nb-iep","src":"config/oprep-3nb-cfg.json","srcurl":"https://usmtf.specchain.org/oprep-3nb/file/config","path":"config/oprep-3nb-cfg.json","description":"OPREP-3NB XML Information Exchange Package"},{"title":"OPREP-3NUS","name":"oprep-3nus-iep","src":"config/oprep-3nus-cfg.json","srcurl":"https://usmtf.specchain.org/oprep-3nus/file/config","path":"config/oprep-3nus-cfg.json","description":"OPREP-3NUS XML Information Exchange Package"},{"title":"OPREP-3P","name":"oprep-3p-iep","src":"config/oprep-3p-cfg.json","srcurl":"https://usmtf.specchain.org/oprep-3p/file/config","path":"config/oprep-3p-cfg.json","description":"OPREP-3P XML Information Exchange Package"},{"title":"OPREP-3PBA","name":"oprep-3pba-iep","src":"config/oprep-3pba-cfg.json","srcurl":"https://usmtf.specchain.org/oprep-3pba/file/config","path":"config/oprep-3pba-cfg.json","description":"OPREP-3PBA XML Information Exchange Package"},{"title":"OPREP-3PCA","name":"oprep-3pca-iep","src":"config/oprep-3pca-cfg.json","srcurl":"https://usmtf.specchain.org/oprep-3pca/file/config","path":"config/oprep-3pca-cfg.json","description":"OPREP-3PCA XML Information Exchange Package"},{"title":"OPREP-3PED","name":"oprep-3ped-iep","src":"config/oprep-3ped-cfg.json","srcurl":"https://usmtf.specchain.org/oprep-3ped/file/config","path":"config/oprep-3ped-cfg.json","description":"OPREP-3PED XML Information Exchange Package"},{"title":"OPREP-3PEV","name":"oprep-3pev-iep","src":"config/oprep-3pev-cfg.json","srcurl":"https://usmtf.specchain.org/oprep-3pev/file/config","path":"config/oprep-3pev-cfg.json","description":"OPREP-3PEV XML Information Exchange Package"},{"title":"OPREP-3PEQ","name":"oprep-3peq-iep","src":"config/oprep-3peq-cfg.json","srcurl":"https://usmtf.specchain.org/oprep-3peq/file/config","path":"config/oprep-3peq-cfg.json","description":"OPREP-3PEQ XML Information Exchange Package"},{"title":"OPREP-3PFB","name":"oprep-3pfb-iep","src":"config/oprep-3pfb-cfg.json","srcurl":"https://usmtf.specchain.org/oprep-3pfb/file/config","path":"config/oprep-3pfb-cfg.json","description":"OPREP-3PFB XML Information Exchange Package"},{"title":"OPREP-3PLSOA","name":"oprep-3plsoa-iep","src":"config/oprep-3plsoa-cfg.json","srcurl":"https://usmtf.specchain.org/oprep-3plsoa/file/config","path":"config/oprep-3plsoa-cfg.json","description":"OPREP-3PLSOA XML Information Exchange Package"},{"title":"OPREP-3PNF","name":"oprep-3pnf-iep","src":"config/oprep-3pnf-cfg.json","srcurl":"https://usmtf.specchain.org/oprep-3pnf/file/config","path":"config/oprep-3pnf-cfg.json","description":"OPREP-3PNF XML Information Exchange Package"},{"title":"OPREP-3WP","name":"oprep-3wp-iep","src":"config/oprep-3wp-cfg.json","srcurl":"https://usmtf.specchain.org/oprep-3wp/file/config","path":"config/oprep-3wp-cfg.json","description":"OPREP-3WP XML Information Exchange Package"},{"title":"OTLNEWS","name":"otlnews-iep","src":"config/otlnews-cfg.json","srcurl":"https://usmtf.specchain.org/otlnews/file/config","path":"config/otlnews-cfg.json","description":"OTLNEWS XML Information Exchange Package"},{"title":"ORDER","name":"order-iep","src":"config/order-cfg.json","srcurl":"https://usmtf.specchain.org/order/file/config","path":"config/order-cfg.json","description":"ORDER XML Information Exchange Package"},{"title":"OBREP","name":"obrep-iep","src":"config/obrep-cfg.json","srcurl":"https://usmtf.specchain.org/obrep/file/config","path":"config/obrep-cfg.json","description":"OBREP XML Information Exchange Package"},{"title":"P4","name":"p4-iep","src":"config/p4-cfg.json","srcurl":"https://usmtf.specchain.org/p4/file/config","path":"config/p4-cfg.json","description":"P4 XML Information Exchange Package"},{"title":"PERSTAT","name":"perstat-iep","src":"config/perstat-cfg.json","srcurl":"https://usmtf.specchain.org/perstat/file/config","path":"config/perstat-cfg.json","description":"PERSTAT XML Information Exchange Package"},{"title":"PSYOPREP","name":"psyoprep-iep","src":"config/psyoprep-cfg.json","srcurl":"https://usmtf.specchain.org/psyoprep/file/config","path":"config/psyoprep-cfg.json","description":"PSYOPREP XML Information Exchange Package"},{"title":"RAPSTAT","name":"rapstat-iep","src":"config/rapstat-cfg.json","srcurl":"https://usmtf.specchain.org/rapstat/file/config","path":"config/rapstat-cfg.json","description":"RAPSTAT XML Information Exchange Package"},{"title":"RASACT","name":"rasact-iep","src":"config/rasact-cfg.json","srcurl":"https://usmtf.specchain.org/rasact/file/config","path":"config/rasact-cfg.json","description":"RASACT XML Information Exchange Package"},{"title":"RASREQ","name":"rasreq-iep","src":"config/rasreq-cfg.json","srcurl":"https://usmtf.specchain.org/rasreq/file/config","path":"config/rasreq-cfg.json","description":"RASREQ XML Information Exchange Package"},{"title":"SITENOM","name":"sitenom-iep","src":"config/sitenom-cfg.json","srcurl":"https://usmtf.specchain.org/sitenom/file/config","path":"config/sitenom-cfg.json","description":"SITENOM XML Information Exchange Package"},{"title":"RECCEXREP","name":"reccexrep-iep","src":"config/reccexrep-cfg.json","srcurl":"https://usmtf.specchain.org/reccexrep/file/config","path":"config/reccexrep-cfg.json","description":"RECCEXREP XML Information Exchange Package"},{"title":"RECON4","name":"recon4-iep","src":"config/recon4-cfg.json","srcurl":"https://usmtf.specchain.org/recon4/file/config","path":"config/recon4-cfg.json","description":"RECON4 XML Information Exchange Package"},{"title":"RECON1","name":"recon1-iep","src":"config/recon1-cfg.json","srcurl":"https://usmtf.specchain.org/recon1/file/config","path":"config/recon1-cfg.json","description":"RECON1 XML Information Exchange Package"},{"title":"RECON3","name":"recon3-iep","src":"config/recon3-cfg.json","srcurl":"https://usmtf.specchain.org/recon3/file/config","path":"config/recon3-cfg.json","description":"RECON3 XML Information Exchange Package"},{"title":"RECON2","name":"recon2-iep","src":"config/recon2-cfg.json","srcurl":"https://usmtf.specchain.org/recon2/file/config","path":"config/recon2-cfg.json","description":"RECON2 XML Information Exchange Package"},{"title":"RI","name":"ri-iep","src":"config/ri-cfg.json","srcurl":"https://usmtf.specchain.org/ri/file/config","path":"config/ri-cfg.json","description":"RI XML Information Exchange Package"},{"title":"RESOURCES","name":"resources-iep","src":"config/resources-cfg.json","srcurl":"https://usmtf.specchain.org/resources/file/config","path":"config/resources-cfg.json","description":"RESOURCES XML Information Exchange Package"},{"title":"RRI","name":"rri-iep","src":"config/rri-cfg.json","srcurl":"https://usmtf.specchain.org/rri/file/config","path":"config/rri-cfg.json","description":"RRI XML Information Exchange Package"},{"title":"ROADCLRREQ","name":"roadclrreq-iep","src":"config/roadclrreq-cfg.json","srcurl":"https://usmtf.specchain.org/roadclrreq/file/config","path":"config/roadclrreq-cfg.json","description":"ROADCLRREQ XML Information Exchange Package"},{"title":"ROADCLRRES","name":"roadclrres-iep","src":"config/roadclrres-cfg.json","srcurl":"https://usmtf.specchain.org/roadclrres/file/config","path":"config/roadclrres-cfg.json","description":"ROADCLRRES XML Information Exchange Package"},{"title":"ROEAUTH","name":"roeauth-iep","src":"config/roeauth-cfg.json","srcurl":"https://usmtf.specchain.org/roeauth/file/config","path":"config/roeauth-cfg.json","description":"ROEAUTH XML Information Exchange Package"},{"title":"ROEIMPL","name":"roeimpl-iep","src":"config/roeimpl-cfg.json","srcurl":"https://usmtf.specchain.org/roeimpl/file/config","path":"config/roeimpl-cfg.json","description":"ROEIMPL XML Information Exchange Package"},{"title":"ROEREQ","name":"roereq-iep","src":"config/roereq-cfg.json","srcurl":"https://usmtf.specchain.org/roereq/file/config","path":"config/roereq-cfg.json","description":"ROEREQ XML Information Exchange Package"},{"title":"SEARCHPLAN","name":"searchplan-iep","src":"config/searchplan-cfg.json","srcurl":"https://usmtf.specchain.org/searchplan/file/config","path":"config/searchplan-cfg.json","description":"SEARCHPLAN XML Information Exchange Package"},{"title":"SARIR","name":"sarir-iep","src":"config/sarir-cfg.json","srcurl":"https://usmtf.specchain.org/sarir/file/config","path":"config/sarir-cfg.json","description":"SARIR XML Information Exchange Package"},{"title":"SARREQ","name":"sarreq-iep","src":"config/sarreq-cfg.json","srcurl":"https://usmtf.specchain.org/sarreq/file/config","path":"config/sarreq-cfg.json","description":"SARREQ XML Information Exchange Package"},{"title":"SARSIT","name":"sarsit-iep","src":"config/sarsit-cfg.json","srcurl":"https://usmtf.specchain.org/sarsit/file/config","path":"config/sarsit-cfg.json","description":"SARSIT XML Information Exchange Package"},{"title":"SENREP","name":"senrep-iep","src":"config/senrep-cfg.json","srcurl":"https://usmtf.specchain.org/senrep/file/config","path":"config/senrep-cfg.json","description":"SENREP XML Information Exchange Package"},{"title":"SENSOREP","name":"sensorep-iep","src":"config/sensorep-cfg.json","srcurl":"https://usmtf.specchain.org/sensorep/file/config","path":"config/sensorep-cfg.json","description":"SENSOREP XML Information Exchange Package"},{"title":"SVRWX","name":"svrwx-iep","src":"config/svrwx-cfg.json","srcurl":"https://usmtf.specchain.org/svrwx/file/config","path":"config/svrwx-cfg.json","description":"SVRWX XML Information Exchange Package"},{"title":"SHIPSTATREP","name":"shipstatrep-iep","src":"config/shipstatrep-cfg.json","srcurl":"https://usmtf.specchain.org/shipstatrep/file/config","path":"config/shipstatrep-cfg.json","description":"SHIPSTATREP XML Information Exchange Package"},{"title":"SIEPCM","name":"siepcm-iep","src":"config/siepcm-cfg.json","srcurl":"https://usmtf.specchain.org/siepcm/file/config","path":"config/siepcm-cfg.json","description":"SIEPCM XML Information Exchange Package"},{"title":"SITECONF","name":"siteconf-iep","src":"config/siteconf-cfg.json","srcurl":"https://usmtf.specchain.org/siteconf/file/config","path":"config/siteconf-cfg.json","description":"SITECONF XML Information Exchange Package"},{"title":"SORTIEALOT","name":"sortiealot-iep","src":"config/sortiealot-cfg.json","srcurl":"https://usmtf.specchain.org/sortiealot/file/config","path":"config/sortiealot-cfg.json","description":"SORTIEALOT XML Information Exchange Package"},{"title":"STO","name":"sto-iep","src":"config/sto-cfg.json","srcurl":"https://usmtf.specchain.org/sto/file/config","path":"config/sto-cfg.json","description":"STO XML Information Exchange Package"},{"title":"SPIREP","name":"spirep-iep","src":"config/spirep-cfg.json","srcurl":"https://usmtf.specchain.org/spirep/file/config","path":"config/spirep-cfg.json","description":"SPIREP XML Information Exchange Package"},{"title":"SORTSREP","name":"sortsrep-iep","src":"config/sortsrep-cfg.json","srcurl":"https://usmtf.specchain.org/sortsrep/file/config","path":"config/sortsrep-cfg.json","description":"SORTSREP XML Information Exchange Package"},{"title":"SORTSREPAF","name":"sortsrepaf-iep","src":"config/sortsrepaf-cfg.json","srcurl":"https://usmtf.specchain.org/sortsrepaf/file/config","path":"config/sortsrepaf-cfg.json","description":"SORTSREPAF XML Information Exchange Package"},{"title":"SORTSREPAR","name":"sortsrepar-iep","src":"config/sortsrepar-cfg.json","srcurl":"https://usmtf.specchain.org/sortsrepar/file/config","path":"config/sortsrepar-cfg.json","description":"SORTSREPAR XML Information Exchange Package"},{"title":"SORTSREPNV","name":"sortsrepnv-iep","src":"config/sortsrepnv-cfg.json","srcurl":"https://usmtf.specchain.org/sortsrepnv/file/config","path":"config/sortsrepnv-cfg.json","description":"SORTSREPNV XML Information Exchange Package"},{"title":"STOPJAMMING","name":"stopjamming-iep","src":"config/stopjamming-cfg.json","srcurl":"https://usmtf.specchain.org/stopjamming/file/config","path":"config/stopjamming-cfg.json","description":"STOPJAMMING XML Information Exchange Package"},{"title":"STRKFCST","name":"strkfcst-iep","src":"config/strkfcst-cfg.json","srcurl":"https://usmtf.specchain.org/strkfcst/file/config","path":"config/strkfcst-cfg.json","description":"STRKFCST XML Information Exchange Package"},{"title":"SUBNOI","name":"subnoi-iep","src":"config/subnoi-cfg.json","srcurl":"https://usmtf.specchain.org/subnoi/file/config","path":"config/subnoi-cfg.json","description":"SUBNOI XML Information Exchange Package"},{"title":"SUBDANGER","name":"subdanger-iep","src":"config/subdanger-cfg.json","srcurl":"https://usmtf.specchain.org/subdanger/file/config","path":"config/subdanger-cfg.json","description":"SUBDANGER XML Information Exchange Package"},{"title":"SUBNOTE","name":"subnote-iep","src":"config/subnote-cfg.json","srcurl":"https://usmtf.specchain.org/subnote/file/config","path":"config/subnote-cfg.json","description":"SUBNOTE XML Information Exchange Package"},{"title":"SUBNOTECHANGE","name":"subnotechange-iep","src":"config/subnotechange-cfg.json","srcurl":"https://usmtf.specchain.org/subnotechange/file/config","path":"config/subnotechange-cfg.json","description":"SUBNOTECHANGE XML Information Exchange Package"},{"title":"SUBNOTECHANGEREQ","name":"subnotechangereq-iep","src":"config/subnotechangereq-cfg.json","srcurl":"https://usmtf.specchain.org/subnotechangereq/file/config","path":"config/subnotechangereq-cfg.json","description":"SUBNOTECHANGEREQ XML Information Exchange Package"},{"title":"SUBNOTEREQ","name":"subnotereq-iep","src":"config/subnotereq-cfg.json","srcurl":"https://usmtf.specchain.org/subnotereq/file/config","path":"config/subnotereq-cfg.json","description":"SUBNOTEREQ XML Information Exchange Package"},{"title":"SUBOPSKED","name":"subopsked-iep","src":"config/subopsked-cfg.json","srcurl":"https://usmtf.specchain.org/subopsked/file/config","path":"config/subopsked-cfg.json","description":"SUBOPSKED XML Information Exchange Package"},{"title":"SUBOPSKEDCHANGE","name":"subopskedchange-iep","src":"config/subopskedchange-cfg.json","srcurl":"https://usmtf.specchain.org/subopskedchange/file/config","path":"config/subopskedchange-cfg.json","description":"SUBOPSKEDCHANGE XML Information Exchange Package"},{"title":"NUDETSUM","name":"nudetsum-iep","src":"config/nudetsum-cfg.json","srcurl":"https://usmtf.specchain.org/nudetsum/file/config","path":"config/nudetsum-cfg.json","description":"NUDETSUM XML Information Exchange Package"},{"title":"SUPCONSTRAINT","name":"supconstraint-iep","src":"config/supconstraint-cfg.json","srcurl":"https://usmtf.specchain.org/supconstraint/file/config","path":"config/supconstraint-cfg.json","description":"SUPCONSTRAINT XML Information Exchange Package"},{"title":"SPRTAIRCOR","name":"sprtaircor-iep","src":"config/sprtaircor-cfg.json","srcurl":"https://usmtf.specchain.org/sprtaircor/file/config","path":"config/sprtaircor-cfg.json","description":"SPRTAIRCOR XML Information Exchange Package"},{"title":"SPRTGEOM","name":"sprtgeom-iep","src":"config/sprtgeom-cfg.json","srcurl":"https://usmtf.specchain.org/sprtgeom/file/config","path":"config/sprtgeom-cfg.json","description":"SPRTGEOM XML Information Exchange Package"},{"title":"SPRTDAACAT","name":"sprtdaacat-iep","src":"config/sprtdaacat-cfg.json","srcurl":"https://usmtf.specchain.org/sprtdaacat/file/config","path":"config/sprtdaacat-cfg.json","description":"SPRTDAACAT XML Information Exchange Package"},{"title":"SYSRRM","name":"sysrrm-iep","src":"config/sysrrm-cfg.json","srcurl":"https://usmtf.specchain.org/sysrrm/file/config","path":"config/sysrrm-cfg.json","description":"SYSRRM XML Information Exchange Package"},{"title":"SYSRFR","name":"sysrfr-iep","src":"config/sysrfr-cfg.json","srcurl":"https://usmtf.specchain.org/sysrfr/file/config","path":"config/sysrfr-cfg.json","description":"SYSRFR XML Information Exchange Package"},{"title":"TAS","name":"tas-iep","src":"config/tas-cfg.json","srcurl":"https://usmtf.specchain.org/tas/file/config","path":"config/tas-cfg.json","description":"TAS XML Information Exchange Package"},{"title":"TACELINT","name":"tacelint-iep","src":"config/tacelint-cfg.json","srcurl":"https://usmtf.specchain.org/tacelint/file/config","path":"config/tacelint-cfg.json","description":"TACELINT XML Information Exchange Package"},{"title":"TACMASINTREP","name":"tacmasintrep-iep","src":"config/tacmasintrep-cfg.json","srcurl":"https://usmtf.specchain.org/tacmasintrep/file/config","path":"config/tacmasintrep-cfg.json","description":"TACMASINTREP XML Information Exchange Package"},{"title":"TACOPDAT","name":"tacopdat-iep","src":"config/tacopdat-cfg.json","srcurl":"https://usmtf.specchain.org/tacopdat/file/config","path":"config/tacopdat-cfg.json","description":"TACOPDAT XML Information Exchange Package"},{"title":"TACREP","name":"tacrep-iep","src":"config/tacrep-cfg.json","srcurl":"https://usmtf.specchain.org/tacrep/file/config","path":"config/tacrep-cfg.json","description":"TACREP XML Information Exchange Package"},{"title":"TARBUL","name":"tarbul-iep","src":"config/tarbul-cfg.json","srcurl":"https://usmtf.specchain.org/tarbul/file/config","path":"config/tarbul-cfg.json","description":"TARBUL XML Information Exchange Package"},{"title":"TGTINFOREP","name":"tgtinforep-iep","src":"config/tgtinforep-cfg.json","srcurl":"https://usmtf.specchain.org/tgtinforep/file/config","path":"config/tgtinforep-cfg.json","description":"TGTINFOREP XML Information Exchange Package"},{"title":"TIDAT","name":"tidat-iep","src":"config/tidat-cfg.json","srcurl":"https://usmtf.specchain.org/tidat/file/config","path":"config/tidat-cfg.json","description":"TIDAT XML Information Exchange Package"},{"title":"TEMPBURIALSITEREQ","name":"tempburialsitereq-iep","src":"config/tempburialsitereq-cfg.json","srcurl":"https://usmtf.specchain.org/tempburialsitereq/file/config","path":"config/tempburialsitereq-cfg.json","description":"TEMPBURIALSITEREQ XML Information Exchange Package"},{"title":"TIR","name":"tir-iep","src":"config/tir-cfg.json","srcurl":"https://usmtf.specchain.org/tir/file/config","path":"config/tir-cfg.json","description":"TIR XML Information Exchange Package"},{"title":"TRANSSPTREQ","name":"transsptreq-iep","src":"config/transsptreq-cfg.json","srcurl":"https://usmtf.specchain.org/transsptreq/file/config","path":"config/transsptreq-cfg.json","description":"TRANSSPTREQ XML Information Exchange Package"},{"title":"TRANSSPTRES","name":"transsptres-iep","src":"config/transsptres-cfg.json","srcurl":"https://usmtf.specchain.org/transsptres/file/config","path":"config/transsptres-cfg.json","description":"TRANSSPTRES XML Information Exchange Package"},{"title":"UHFACCESSAPPR","name":"uhfaccessappr-iep","src":"config/uhfaccessappr-cfg.json","srcurl":"https://usmtf.specchain.org/uhfaccessappr/file/config","path":"config/uhfaccessappr-cfg.json","description":"UHFACCESSAPPR XML Information Exchange Package"},{"title":"UHFCANCEL","name":"uhfcancel-iep","src":"config/uhfcancel-cfg.json","srcurl":"https://usmtf.specchain.org/uhfcancel/file/config","path":"config/uhfcancel-cfg.json","description":"UHFCANCEL XML Information Exchange Package"},{"title":"UHFACCESSCHANGE","name":"uhfaccesschange-iep","src":"config/uhfaccesschange-cfg.json","srcurl":"https://usmtf.specchain.org/uhfaccesschange/file/config","path":"config/uhfaccesschange-cfg.json","description":"UHFACCESSCHANGE XML Information Exchange Package"},{"title":"UHFDISAPPROVE","name":"uhfdisapprove-iep","src":"config/uhfdisapprove-cfg.json","srcurl":"https://usmtf.specchain.org/uhfdisapprove/file/config","path":"config/uhfdisapprove-cfg.json","description":"UHFDISAPPROVE XML Information Exchange Package"},{"title":"UHFPREEMPT","name":"uhfpreempt-iep","src":"config/uhfpreempt-cfg.json","srcurl":"https://usmtf.specchain.org/uhfpreempt/file/config","path":"config/uhfpreempt-cfg.json","description":"UHFPREEMPT XML Information Exchange Package"},{"title":"UHFACCESSREQ","name":"uhfaccessreq-iep","src":"config/uhfaccessreq-cfg.json","srcurl":"https://usmtf.specchain.org/uhfaccessreq/file/config","path":"config/uhfaccessreq-cfg.json","description":"UHFACCESSREQ XML Information Exchange Package"},{"title":"UHFTERMINATE","name":"uhfterminate-iep","src":"config/uhfterminate-cfg.json","srcurl":"https://usmtf.specchain.org/uhfterminate/file/config","path":"config/uhfterminate-cfg.json","description":"UHFTERMINATE XML Information Exchange Package"},{"title":"ULNUICRPT","name":"ulnuicrpt-iep","src":"config/ulnuicrpt-cfg.json","srcurl":"https://usmtf.specchain.org/ulnuicrpt/file/config","path":"config/ulnuicrpt-cfg.json","description":"ULNUICRPT XML Information Exchange Package"},{"title":"VDSNOTE","name":"vdsnote-iep","src":"config/vdsnote-cfg.json","srcurl":"https://usmtf.specchain.org/vdsnote/file/config","path":"config/vdsnote-cfg.json","description":"VDSNOTE XML Information Exchange Package"},{"title":"VISITREQ","name":"visitreq-iep","src":"config/visitreq-cfg.json","srcurl":"https://usmtf.specchain.org/visitreq/file/config","path":"config/visitreq-cfg.json","description":"VISITREQ XML Information Exchange Package"},{"title":"WTRSUPPT","name":"wtrsuppt-iep","src":"config/wtrsuppt-cfg.json","srcurl":"https://usmtf.specchain.org/wtrsuppt/file/config","path":"config/wtrsuppt-cfg.json","description":"WTRSUPPT XML Information Exchange Package"},{"title":"WXFCST","name":"wxfcst-iep","src":"config/wxfcst-cfg.json","srcurl":"https://usmtf.specchain.org/wxfcst/file/config","path":"config/wxfcst-cfg.json","description":"WXFCST XML Information Exchange Package"},{"title":"WXOBS","name":"wxobs-iep","src":"config/wxobs-cfg.json","srcurl":"https://usmtf.specchain.org/wxobs/file/config","path":"config/wxobs-cfg.json","description":"WXOBS XML Information Exchange Package"}]}